<?xml version="1.0" encoding="UTF-8"?>
<entity_profile>
  <profile id="Logistician" name="Logistician"/>
  <profile id="Translator" name="Translator"/>
  <profile id="Salesman" name="Salesman"/>
  <profile id="ad" name="iste"/>
  <profile id="sequi" name="adipisci"/>
  <profile id="facilis" name="ut"/>
  <profile id="libero" name="quia"/>
  <profile id="omnis" name="alias"/>
  <profile id="dolor" name="molestiae"/>
  <profile id="quod" name="velit"/>
  <profile id="ut" name="facilis"/>
  <profile id="itaque" name="eum"/>
  <profile id="et" name="consectetur"/>
</entity_profile>
