<?xml version="1.0" encoding="UTF-8"?>
<entity_range_weight>
  <fields class="RangeWeight">
    <field name="id_carrier" relation="carrier"/>
    <field name="delimiter1"/>
    <field name="delimiter2"/>
  </fields>
  <entities>
    <range_weight id_carrier="My_carrier" id="1" delimiter2="7082" delimiter1="0"/>
    <range_weight id_carrier="My_carrier" id="2" delimiter2="3180" delimiter1="0"/>
    <range_weight id_carrier="quam" id="3" delimiter2="2976" delimiter1="0"/>
    <range_weight id_carrier="My_carrier" id="4" delimiter2="9559" delimiter1="0"/>
    <range_weight id_carrier="carrier_1" id="5" delimiter2="2164" delimiter1="0"/>
    <range_weight id_carrier="My_carrier" id="6" delimiter2="4338" delimiter1="0"/>
    <range_weight id_carrier="quam" id="7" delimiter2="6725" delimiter1="0"/>
    <range_weight id_carrier="My_carrier" id="8" delimiter2="3540" delimiter1="0"/>
    <range_weight id_carrier="carrier_1" id="9" delimiter2="1305" delimiter1="0"/>
    <range_weight id_carrier="carrier_1" id="10" delimiter2="1012" delimiter1="0"/>
    <range_weight id_carrier="carrier_1" id="11" delimiter2="7672" delimiter1="0"/>
    <range_weight id_carrier="carrier_1" id="12" delimiter2="8176" delimiter1="0"/>
    <range_weight id_carrier="My_carrier" id="13" delimiter2="7762" delimiter1="0"/>
    <range_weight id_carrier="carrier_1" id="14" delimiter2="2724" delimiter1="0"/>
    <range_weight id_carrier="My_carrier" id="15" delimiter2="2338" delimiter1="0"/>
    <range_weight id_carrier="My_carrier" id="16" delimiter2="1188" delimiter1="0"/>
    <range_weight id_carrier="carrier_1" id="17" delimiter2="5077" delimiter1="0"/>
    <range_weight id_carrier="carrier_1" id="18" delimiter2="7393" delimiter1="0"/>
    <range_weight id_carrier="quam" id="19" delimiter2="5384" delimiter1="0"/>
    <range_weight id_carrier="quam" id="20" delimiter2="8114" delimiter1="0"/>
    <range_weight id_carrier="carrier_1" id="21" delimiter2="6747" delimiter1="0"/>
    <range_weight id_carrier="carrier_1" id="22" delimiter2="4752" delimiter1="0"/>
    <range_weight id_carrier="carrier_1" id="23" delimiter2="6265" delimiter1="0"/>
    <range_weight id_carrier="My_carrier" id="24" delimiter2="7428" delimiter1="0"/>
    <range_weight id_carrier="quam" id="25" delimiter2="3366" delimiter1="0"/>
    <range_weight id_carrier="carrier_1" id="26" delimiter2="4678" delimiter1="0"/>
    <range_weight id_carrier="quam" id="27" delimiter2="4254" delimiter1="0"/>
    <range_weight id_carrier="My_carrier" id="28" delimiter2="6683" delimiter1="0"/>
    <range_weight id_carrier="My_carrier" id="29" delimiter2="1944" delimiter1="0"/>
    <range_weight id_carrier="My_carrier" id="30" delimiter2="6342" delimiter1="0"/>
    <range_weight id_carrier="carrier_1" id="31" delimiter2="4822" delimiter1="0"/>
    <range_weight id_carrier="My_carrier" id="32" delimiter2="7372" delimiter1="0"/>
    <range_weight id_carrier="carrier_1" id="33" delimiter2="9578" delimiter1="0"/>
    <range_weight id_carrier="carrier_1" id="34" delimiter2="8639" delimiter1="0"/>
    <range_weight id_carrier="quam" id="35" delimiter2="2177" delimiter1="0"/>
    <range_weight id_carrier="quam" id="36" delimiter2="3812" delimiter1="0"/>
    <range_weight id_carrier="quam" id="37" delimiter2="8130" delimiter1="0"/>
    <range_weight id_carrier="carrier_1" id="38" delimiter2="4008" delimiter1="0"/>
    <range_weight id_carrier="carrier_1" id="39" delimiter2="3026" delimiter1="0"/>
    <range_weight id_carrier="My_carrier" id="40" delimiter2="9327" delimiter1="0"/>
    <range_weight id_carrier="quam" id="41" delimiter2="3651" delimiter1="0"/>
    <range_weight id_carrier="quam" id="42" delimiter2="1895" delimiter1="0"/>
    <range_weight id_carrier="carrier_1" id="43" delimiter2="6015" delimiter1="0"/>
    <range_weight id_carrier="carrier_1" id="44" delimiter2="1266" delimiter1="0"/>
    <range_weight id_carrier="quam" id="45" delimiter2="3796" delimiter1="0"/>
    <range_weight id_carrier="quam" id="46" delimiter2="6806" delimiter1="0"/>
    <range_weight id_carrier="My_carrier" id="47" delimiter2="8154" delimiter1="0"/>
    <range_weight id_carrier="carrier_1" id="48" delimiter2="9856" delimiter1="0"/>
    <range_weight id_carrier="My_carrier" id="49" delimiter2="8770" delimiter1="0"/>
    <range_weight id_carrier="carrier_1" id="50" delimiter2="8523" delimiter1="0"/>
    <range_weight id_carrier="carrier_1" id="51" delimiter2="3491" delimiter1="0"/>
    <range_weight id_carrier="My_carrier" id="52" delimiter2="7348" delimiter1="0"/>
    <range_weight id_carrier="quam" id="53" delimiter2="9139" delimiter1="0"/>
    <range_weight id_carrier="carrier_1" id="54" delimiter2="9898" delimiter1="0"/>
    <range_weight id_carrier="quam" id="55" delimiter2="8695" delimiter1="0"/>
    <range_weight id_carrier="carrier_1" id="56" delimiter2="2150" delimiter1="0"/>
    <range_weight id_carrier="carrier_1" id="57" delimiter2="9501" delimiter1="0"/>
    <range_weight id_carrier="quam" id="58" delimiter2="4106" delimiter1="0"/>
    <range_weight id_carrier="carrier_1" id="59" delimiter2="5881" delimiter1="0"/>
    <range_weight id_carrier="carrier_1" id="60" delimiter2="3886" delimiter1="0"/>
    <range_weight id_carrier="carrier_1" id="61" delimiter2="4797" delimiter1="0"/>
    <range_weight id_carrier="My_carrier" id="62" delimiter2="6082" delimiter1="0"/>
    <range_weight id_carrier="carrier_1" id="63" delimiter2="4873" delimiter1="0"/>
    <range_weight id_carrier="carrier_1" id="64" delimiter2="7654" delimiter1="0"/>
    <range_weight id_carrier="My_carrier" id="65" delimiter2="5508" delimiter1="0"/>
    <range_weight id_carrier="quam" id="66" delimiter2="3666" delimiter1="0"/>
    <range_weight id_carrier="quam" id="67" delimiter2="7625" delimiter1="0"/>
    <range_weight id_carrier="quam" id="68" delimiter2="8951" delimiter1="0"/>
    <range_weight id_carrier="carrier_1" id="69" delimiter2="7267" delimiter1="0"/>
    <range_weight id_carrier="carrier_1" id="70" delimiter2="8506" delimiter1="0"/>
    <range_weight id_carrier="My_carrier" id="71" delimiter2="9281" delimiter1="0"/>
    <range_weight id_carrier="carrier_1" id="72" delimiter2="1528" delimiter1="0"/>
    <range_weight id_carrier="quam" id="73" delimiter2="2200" delimiter1="0"/>
    <range_weight id_carrier="My_carrier" id="74" delimiter2="8812" delimiter1="0"/>
    <range_weight id_carrier="carrier_1" id="75" delimiter2="1452" delimiter1="0"/>
    <range_weight id_carrier="quam" id="76" delimiter2="3879" delimiter1="0"/>
    <range_weight id_carrier="carrier_1" id="77" delimiter2="8235" delimiter1="0"/>
    <range_weight id_carrier="My_carrier" id="78" delimiter2="1797" delimiter1="0"/>
    <range_weight id_carrier="My_carrier" id="79" delimiter2="3068" delimiter1="0"/>
    <range_weight id_carrier="quam" id="80" delimiter2="2858" delimiter1="0"/>
    <range_weight id_carrier="carrier_1" id="81" delimiter2="8222" delimiter1="0"/>
    <range_weight id_carrier="quam" id="82" delimiter2="4223" delimiter1="0"/>
    <range_weight id_carrier="quam" id="83" delimiter2="2107" delimiter1="0"/>
    <range_weight id_carrier="My_carrier" id="84" delimiter2="2165" delimiter1="0"/>
    <range_weight id_carrier="quam" id="85" delimiter2="3309" delimiter1="0"/>
    <range_weight id_carrier="carrier_1" id="86" delimiter2="5915" delimiter1="0"/>
    <range_weight id_carrier="quam" id="87" delimiter2="9175" delimiter1="0"/>
    <range_weight id_carrier="My_carrier" id="88" delimiter2="3978" delimiter1="0"/>
    <range_weight id_carrier="quam" id="89" delimiter2="4729" delimiter1="0"/>
    <range_weight id_carrier="quam" id="90" delimiter2="2273" delimiter1="0"/>
    <range_weight id_carrier="carrier_1" id="91" delimiter2="1322" delimiter1="0"/>
    <range_weight id_carrier="My_carrier" id="92" delimiter2="5891" delimiter1="0"/>
    <range_weight id_carrier="quam" id="93" delimiter2="3889" delimiter1="0"/>
    <range_weight id_carrier="carrier_1" id="94" delimiter2="7701" delimiter1="0"/>
    <range_weight id_carrier="carrier_1" id="95" delimiter2="3372" delimiter1="0"/>
    <range_weight id_carrier="quam" id="96" delimiter2="4738" delimiter1="0"/>
    <range_weight id_carrier="quam" id="97" delimiter2="2828" delimiter1="0"/>
    <range_weight id_carrier="quam" id="98" delimiter2="5073" delimiter1="0"/>
    <range_weight id_carrier="My_carrier" id="99" delimiter2="8624" delimiter1="0"/>
    <range_weight id_carrier="My_carrier" id="100" delimiter2="5828" delimiter1="0"/>
  </entities>
</entity_range_weight>
